rust_tls_client-1.2.1.dist-info/METADATA
rust_tls_client-1.2.1.dist-info/WHEEL
rust_tls_client-1.2.1.dist-info/licenses/LICENSE
rust_tls_client/__init__.py
rust_tls_client/py.typed
rust_tls_client/rust_tls_client.abi3.so
rust_tls_client/rust_tls_client.pyi
rust_tls_client-1.2.1.dist-info/RECORD
