Metadata-Version: 2.4
Name: rust_tls_client
Version: 1.2.1
Classifier: Development Status :: 5 - Production/Stable
Classifier: Intended Audience :: Developers
Classifier: License :: OSI Approved :: MIT License
Classifier: Programming Language :: Python :: 3
Classifier: Programming Language :: Python :: 3.8
Classifier: Programming Language :: Python :: 3.9
Classifier: Programming Language :: Python :: 3.10
Classifier: Programming Language :: Python :: 3.11
Classifier: Programming Language :: Python :: 3.12
Classifier: Programming Language :: Python :: 3.13
Classifier: Programming Language :: Python :: Implementation :: CPython
Classifier: Programming Language :: Rust
Classifier: Topic :: Internet :: WWW/HTTP
Classifier: Topic :: Software Development :: Libraries :: Python Modules
License-File: LICENSE
Summary: 基于原primp 重新优化调整的请求库 - The fastest python HTTP client that can impersonate web browsers
Keywords: requests,httpx,http,http-client,tls-fingerprint,ja3,ja4,impersonate,browser-impersonation,web-scraping,crawler,reverse-engineering
Author: wang
Requires-Python: >=3.8
Project-URL: Homepage, https://github.com/wmm1996528/
